{
  "menuItems": [
    {
      "id": 2,
      "title": "Bipolaritet",
      "slug": "bipolaritet",
      "image": "/images/menu/bipolar.webp",
      "submenuItems": [
        {
          "id": 21,
          "title": "Vad är bipolaritet",
          "slug": "vad-ar-bipolaritet"
        },
        {
          "id": 22,
          "title": "Diagnoser",
          "slug": "diagnoser"
        },
        {
          "id": 23,
          "title": "Symptom",
          "slug": "symptom"
        },
        {
          "id": 24,
          "title": "FAQ",
          "slug": "vanliga-fragor"
        }
      ]
    },
    {
      "id": 3,
      "title": "Anhöriga",
      "slug": "anhoriga",
      "submenuItems": []
    },
    {
      "id": 4,
      "title": "Behandling",
      "slug": "behandling",
      "image": "/images/menu/treatment.webp",
      "submenuItems": [
        {
          "id": 41,
          "title": "Medicinska behandlingar",
          "slug": "medicinska-behandlingar"
        },
        {
          "id": 42,
          "title": "Självhjälp",
          "slug": "sjalvhjalp"
        },
        {
          "id": 43,
          "title": "Terapi",
          "slug": "terapi"
        },
        {
          "id": 44,
          "title": "Verktyg & Dokument",
          "slug": "dokument"
        }
      ]
    },
    {
      "id": 5,
      "title": "Multimedia",
      "slug": "multimedia",
      "image": "/images/menu/multimedia.webp",
      "submenuItems": [
        {
          "id": 51,
          "title": "Filmer",
          "slug": "filmer"
        },
        {
          "id": 52,
          "title": "Podcasts",
          "slug": "podcasts"
        },
        {
          "id": 53,
          "title": "Musik",
          "slug": "musik"
        },
        {
          "id": 54,
          "title": "Böcker",
          "slug": "bocker"
        }
      ]
    },
    {
      "id": 6,
      "title": "Forskning",
      "slug": "forskning",
      "image": "/images/forskning.png",
      "submenuItems": []
    },
    {
      "id": 7,
      "title": "Hjälp",
      "slug": "hjalp",
      "image": "/images/help/hand-shake.webp",
      "submenuItems": [
        {
          "id": 71,
          "title": "Myndigheter",
          "slug": "myndigheter"
        },
        {
          "id": 72,
          "title": "Juridik och rättigheter",
          "slug": "juridik-och-raattigheter"
        },
        {
          "id": 73,
          "title": "Ekonomisk hjälp",
          "slug": "ekonomisk-hjalp"
        }
      ]
    },
    {
      "id": 8,
      "title": "Om oss",
      "slug": "om-oss",
      "image": "/images/menu/about.webp",
      "submenuItems": [
        {
          "id": 81,
          "title": "Vision",
          "slug": "vision"
        },
        {
          "id": 82,
          "title": "Villkor",
          "slug": "villkor"
        },
        {
          "id": 83,
          "title": "Integritetspolicy",
          "slug": "integritetspolicy"
        },
        {
          "id": 84,
          "title": "Kontakt",
          "slug": "kontakt"
        }
      ]
    }
  ]
}
